Metadata-Version: 1.1
Name: izaber-flask
Version: 1.20180813
Summary: Base load point for iZaber flask
Home-page: https://github.com/zabertech/izaber-flask
Author: Aki Mimoto
Author-email: aki+izaber@zaber.com
License: MIT
Download-URL: https://github.com/zabertech/izaber-flask/archive/1.20180813.tar.gz
Platform: UNKNOWN
